git_config/__init__.py
git_config/git_config.py
git_config-1.0.0.dist-info/LICENSE
git_config-1.0.0.dist-info/METADATA
git_config-1.0.0.dist-info/WHEEL
git_config-1.0.0.dist-info/top_level.txt
git_config-1.0.0.dist-info/RECORD
