Metadata-Version: 2.1
Name: git-config
Version: 1.0.0
Summary: Get local or global git config as a dictionary
Home-page: https://github.com/coderosh/git_config
Author: Roshan Acharya
Author-email: acharyaroshan2357@gmail.com
License: MIT
Project-URL: Documentation, https://github.com/coderosh/git_config#readme
Project-URL: Bug Tracker, https://github.com/coderosh/git_config/issues
Platform: UNKNOWN
Classifier: Programming Language :: Python :: 3
Classifier: License :: OSI Approved :: MIT License
Classifier: Operating System :: OS Independent
Requires-Python: >3
License-File: LICENSE
